[
  {
    "title": "DepEd tightens LGU classroom construction monitoring",
    "source": "BusinessWorld Banking",
    "date": "2026-07-10T08:52:18.000Z",
    "reason_dropped": "low_relevance"
  },
  {
    "title": "Philippines’ net FDI inflows plunge to near 10-year low in April",
    "source": "BusinessWorld Banking",
    "date": "2026-07-10T08:31:20.000Z",
    "reason_dropped": "low_relevance"
  },
  {
    "title": "UP backs rental housing project amid demolition, displacement concerns",
    "source": "BusinessWorld Banking",
    "date": "2026-07-10T08:16:47.000Z",
    "reason_dropped": "low_relevance"
  },
  {
    "title": "Teodoro seeks higher defense spending to bolster maritime security",
    "source": "BusinessWorld Banking",
    "date": "2026-07-10T07:42:23.000Z",
    "reason_dropped": "low_relevance"
  },
  {
    "title": "US tags Pax Silica initiative in Philippines as top priority — DoF",
    "source": "BusinessWorld Banking",
    "date": "2026-07-10T07:23:45.000Z",
    "reason_dropped": "low_relevance"
  },
  {
    "title": "Meralco July power rate rises P0.3428/kWh on higher generation charge",
    "source": "BusinessWorld Banking",
    "date": "2026-07-10T06:27:44.000Z",
    "reason_dropped": "low_relevance"
  },
  {
    "title": "Sandiganbayan rejects Estrada bid to attend Duterte impeachment trial",
    "source": "BusinessWorld Banking",
    "date": "2026-07-10T06:25:36.000Z",
    "reason_dropped": "low_relevance"
  },
  {
    "title": "Bavi, enhanced southwest monsoon to bring heavy rains, strong winds",
    "source": "BusinessWorld Banking",
    "date": "2026-07-10T06:12:10.000Z",
    "reason_dropped": "low_relevance"
  },
  {
    "title": "El Niño, prolonged Middle East war seen keeping Philippine inflation elevated",
    "source": "BusinessWorld Banking",
    "date": "2026-07-09T16:34:09.000Z",
    "reason_dropped": "low_relevance"
  },
  {
    "title": "A decade after Hague win, Filipino fishers still shut out of Scarborough Shoal",
    "source": "BusinessWorld Banking",
    "date": "2026-07-09T16:33:14.000Z",
    "reason_dropped": "low_relevance"
  },
  {
    "title": "DBCC trims revenue goals",
    "source": "BusinessWorld Banking",
    "date": "2026-07-09T16:32:13.000Z",
    "reason_dropped": "low_relevance"
  },
  {
    "title": "Philippines secures $60-M grant from MCC",
    "source": "BusinessWorld Banking",
    "date": "2026-07-09T16:31:13.000Z",
    "reason_dropped": "low_relevance"
  },
  {
    "title": "SM Prime opens P7-billion Cebu arena",
    "source": "BusinessWorld Banking",
    "date": "2026-07-09T16:09:16.000Z",
    "reason_dropped": "low_relevance"
  },
  {
    "title": "Pokémon pop-up store, running event to commemorate 30 years",
    "source": "BusinessWorld Banking",
    "date": "2026-07-09T16:08:40.000Z",
    "reason_dropped": "low_relevance"
  },
  {
    "title": "CTA upholds partial Petron excise tax refunds in twin rulings",
    "source": "BusinessWorld Banking",
    "date": "2026-07-09T16:08:15.000Z",
    "reason_dropped": "low_relevance"
  },
  {
    "title": "BDO eyes at least P5B from sustainability bonds",
    "source": "BusinessWorld Banking",
    "date": "2026-07-09T16:07:21.000Z",
    "reason_dropped": "low_relevance"
  },
  {
    "title": "DMPL cites PHL business, debt restructuring efforts to support continued operations",
    "source": "BusinessWorld Banking",
    "date": "2026-07-09T16:07:15.000Z",
    "reason_dropped": "low_relevance"
  },
  {
    "title": "Cinemalaya 2026 ramps up ahead of return to CCP next year",
    "source": "BusinessWorld Banking",
    "date": "2026-07-09T16:07:09.000Z",
    "reason_dropped": "low_relevance"
  },
  {
    "title": "ICTSI completes Brazil logistics acquisition",
    "source": "BusinessWorld Banking",
    "date": "2026-07-09T16:06:48.000Z",
    "reason_dropped": "low_relevance"
  },
  {
    "title": "Stuff to Do (07/10/26)",
    "source": "BusinessWorld Banking",
    "date": "2026-07-09T16:06:40.000Z",
    "reason_dropped": "low_relevance"
  },
  {
    "title": "PhilWeb partners with Pragmatic Play to expand gaming services",
    "source": "BusinessWorld Banking",
    "date": "2026-07-09T16:05:48.000Z",
    "reason_dropped": "low_relevance"
  },
  {
    "title": "TikTok Shop strengthens beauty discovery with Seoul Glow K-Beauty Campaign",
    "source": "BusinessWorld Banking",
    "date": "2026-07-09T16:05:44.000Z",
    "reason_dropped": "low_relevance"
  },
  {
    "title": "PPA at 52: Modernizing ports towards stronger economic growth",
    "source": "BusinessWorld Banking",
    "date": "2026-07-09T16:05:15.000Z",
    "reason_dropped": "low_relevance"
  },
  {
    "title": "Topline unit, Singapore’s Aesen form offshore services venture",
    "source": "BusinessWorld Banking",
    "date": "2026-07-09T16:04:47.000Z",
    "reason_dropped": "low_relevance"
  },
  {
    "title": "Enhancing the Philippines’ port infrastructure",
    "source": "BusinessWorld Banking",
    "date": "2026-07-09T16:04:33.000Z",
    "reason_dropped": "low_relevance"
  },
  {
    "title": "Democracy on trial: Why the integrity of impeachment matters",
    "source": "BusinessWorld Banking",
    "date": "2026-07-09T16:04:02.000Z",
    "reason_dropped": "low_relevance"
  },
  {
    "title": "MIC, PNOC study Bataan petroleum storage project",
    "source": "BusinessWorld Banking",
    "date": "2026-07-09T16:03:46.000Z",
    "reason_dropped": "low_relevance"
  },
  {
    "title": "LIST: Flights canceled on July 11 due to 'Inday'",
    "source": "Philstar Business",
    "date": "2026-07-11T06:58:00.000Z",
    "reason_dropped": "low_relevance"
  },
  {
    "title": "Lance Gokongwei joins PhilWeb board",
    "source": "Philstar Business",
    "date": "2026-07-10T16:00:00.000Z",
    "reason_dropped": "low_relevance"
  },
  {
    "title": "EVs still on the rise",
    "source": "Philstar Business",
    "date": "2026-07-10T16:00:00.000Z",
    "reason_dropped": "low_relevance"
  },
  {
    "title": "Effective one-on-one meets",
    "source": "Philstar Business",
    "date": "2026-07-10T16:00:00.000Z",
    "reason_dropped": "low_relevance"
  },
  {
    "title": "Pax Silica gains pace as United States, Philippines push AI hub",
    "source": "Philstar Business",
    "date": "2026-07-10T16:00:00.000Z",
    "reason_dropped": "low_relevance"
  },
  {
    "title": "RCBC backs Yuchengco BESS project in Capiz",
    "source": "Philstar Business",
    "date": "2026-07-10T16:00:00.000Z",
    "reason_dropped": "low_relevance"
  },
  {
    "title": "DoubleDragon set to open Japan hotel in December",
    "source": "Philstar Business",
    "date": "2026-07-10T16:00:00.000Z",
    "reason_dropped": "low_relevance"
  },
  {
    "title": "Agricultural trade deficit narrows to $988 million in May",
    "source": "Philstar Business",
    "date": "2026-07-10T16:00:00.000Z",
    "reason_dropped": "low_relevance"
  },
  {
    "title": "PCSO ranks among top-performing GOCCs",
    "source": "Philstar Business",
    "date": "2026-07-10T16:00:00.000Z",
    "reason_dropped": "low_relevance"
  },
  {
    "title": "Shares bounce back on bargain hunting",
    "source": "Philstar Business",
    "date": "2026-07-10T16:00:00.000Z",
    "reason_dropped": "low_relevance"
  },
  {
    "title": "Concert economy goes to Cebu",
    "source": "Philstar Business",
    "date": "2026-07-10T16:00:00.000Z",
    "reason_dropped": "low_relevance"
  },
  {
    "title": "FDI inflows plunge to $250 million in April",
    "source": "Philstar Business",
    "date": "2026-07-10T16:00:00.000Z",
    "reason_dropped": "low_relevance"
  },
  {
    "title": "The rise of human-centered AI: This chatbot learned to speak Filipino",
    "source": "Philstar Business",
    "date": "2026-07-10T06:53:00.000Z",
    "reason_dropped": "low_relevance"
  },
  {
    "title": "PwC Philippines admits four new partners to strengthen leadership across assurance and regional practices",
    "source": "Philstar Business",
    "date": "2026-07-10T06:30:00.000Z",
    "reason_dropped": "low_relevance"
  },
  {
    "title": "BDO’s PHP ASEAN Sustainability Bonds due 2028",
    "source": "Philstar Business",
    "date": "2026-07-10T02:25:00.000Z",
    "reason_dropped": "low_relevance"
  },
  {
    "title": "Why more families are looking north for a smarter first home",
    "source": "Philstar Business",
    "date": "2026-07-10T01:00:00.000Z",
    "reason_dropped": "low_relevance"
  },
  {
    "title": "Moratorium on new online lending firms lifted by August",
    "source": "Philstar Business",
    "date": "2026-07-09T16:00:00.000Z",
    "reason_dropped": "low_relevance"
  },
  {
    "title": "No derailing the revival of Bicol Express – PNR",
    "source": "Philstar Business",
    "date": "2026-07-09T16:00:00.000Z",
    "reason_dropped": "low_relevance"
  },
  {
    "title": "Security Bank marks 75 years",
    "source": "Philstar Business",
    "date": "2026-07-09T16:00:00.000Z",
    "reason_dropped": "low_relevance"
  },
  {
    "title": "GOCC dividends under Marcos top ₱500 billion, exceed Duterte-era haul by 31%",
    "source": "Manila Bulletin Business",
    "date": "2026-07-08T08:54:00.000Z",
    "reason_dropped": "hard_excluded_commerce"
  },
  {
    "title": "BSP urges netizens: Stop printing fake banknotes for online jokes",
    "source": "Manila Bulletin Business",
    "date": "2026-07-11T02:54:00.000Z",
    "reason_dropped": "low_relevance"
  },
  {
    "title": "Diesel braced for big-time oil price jump",
    "source": "Manila Bulletin Business",
    "date": "2026-07-11T01:05:00.000Z",
    "reason_dropped": "low_relevance"
  },
  {
    "title": "How Rafael Consing Jr. is mapping out Maharlika’s ₱1.26B next move",
    "source": "Manila Bulletin Business",
    "date": "2026-07-11T00:00:00.000Z",
    "reason_dropped": "low_relevance"
  },
  {
    "title": "Pagcor orders strict disclosures on foreign gaming ties, launches unified license option",
    "source": "Manila Bulletin Business",
    "date": "2026-07-10T09:00:00.000Z",
    "reason_dropped": "low_relevance"
  },
  {
    "title": "US wants Clark AI hub fast-tracked as regional race heats up",
    "source": "Manila Bulletin Business",
    "date": "2026-07-10T08:25:00.000Z",
    "reason_dropped": "low_relevance"
  },
  {
    "title": "PSEi bounces after US-Iran talks continue despite airstrikes",
    "source": "Manila Bulletin Business",
    "date": "2026-07-10T08:14:00.000Z",
    "reason_dropped": "low_relevance"
  },
  {
    "title": "Foreign direct investment drops 26% through April as debt capital shrinks",
    "source": "Manila Bulletin Business",
    "date": "2026-07-10T07:55:00.000Z",
    "reason_dropped": "low_relevance"
  },
  {
    "title": "SM Cares trains frontlines to build more inclusive malls",
    "source": "Manila Bulletin Business",
    "date": "2026-07-10T07:50:00.000Z",
    "reason_dropped": "low_relevance"
  },
  {
    "title": "Philippines scores near-perfect marks in global debt transparency survey",
    "source": "Manila Bulletin Business",
    "date": "2026-07-10T06:57:00.000Z",
    "reason_dropped": "low_relevance"
  },
  {
    "title": "PSE slaps sanctions on First Gen, DoubleDragon over disclosure failures",
    "source": "Manila Bulletin Business",
    "date": "2026-07-10T06:48:00.000Z",
    "reason_dropped": "low_relevance"
  },
  {
    "title": "Pakistan questions legality of Philippine rice import curbs",
    "source": "Manila Bulletin Business",
    "date": "2026-07-10T06:45:00.000Z",
    "reason_dropped": "low_relevance"
  },
  {
    "title": "Hotel101 nears December opening of record-breaking Japan resort",
    "source": "Manila Bulletin Business",
    "date": "2026-07-10T06:26:00.000Z",
    "reason_dropped": "low_relevance"
  },
  {
    "title": "BIR wins top digital initiative award in Singapore for 2026 tax platform",
    "source": "Manila Bulletin Business",
    "date": "2026-07-10T05:58:00.000Z",
    "reason_dropped": "low_relevance"
  },
  {
    "title": "Meralco raises July power rates, fuel price hikes to follow",
    "source": "Manila Bulletin Business",
    "date": "2026-07-10T05:02:00.000Z",
    "reason_dropped": "low_relevance"
  },
  {
    "title": "Billionaire Lance Gokongwei joins PhilWeb board after ₱2-billion bet",
    "source": "Manila Bulletin Business",
    "date": "2026-07-10T03:12:00.000Z",
    "reason_dropped": "low_relevance"
  },
  {
    "title": "Sy aims to lure Bruno Mars to new Cebu Arena after sold-out BINI debut",
    "source": "Manila Bulletin Business",
    "date": "2026-07-10T03:03:00.000Z",
    "reason_dropped": "low_relevance"
  },
  {
    "title": "ERC moves to block rigged power supply deals",
    "source": "Manila Bulletin Business",
    "date": "2026-07-10T02:43:00.000Z",
    "reason_dropped": "low_relevance"
  },
  {
    "title": "Uncertainty: A test of leadership",
    "source": "Manila Bulletin Business",
    "date": "2026-07-09T16:01:00.000Z",
    "reason_dropped": "low_relevance"
  },
  {
    "title": "Economic team shakes up BIR, Customs targets for 2026",
    "source": "Manila Bulletin Business",
    "date": "2026-07-09T16:00:00.000Z",
    "reason_dropped": "low_relevance"
  },
  {
    "title": "Rice wholesale prices edge down in June but annual pressures linger",
    "source": "Manila Bulletin Business",
    "date": "2026-07-09T09:24:00.000Z",
    "reason_dropped": "low_relevance"
  },
  {
    "title": "Maharlika, PNOC to build first-ever strategic oil reserve by 2028",
    "source": "Manila Bulletin Business",
    "date": "2026-07-09T09:21:00.000Z",
    "reason_dropped": "low_relevance"
  },
  {
    "title": "Stocks snap six-day rally as Trump’s Iran warning rattles markets",
    "source": "Manila Bulletin Business",
    "date": "2026-07-09T09:13:00.000Z",
    "reason_dropped": "low_relevance"
  },
  {
    "title": "Del Monte defends solvency after SGX raises going concern warnings",
    "source": "Manila Bulletin Business",
    "date": "2026-07-09T08:57:00.000Z",
    "reason_dropped": "low_relevance"
  },
  {
    "title": "Therma Marine named top real property taxpayer in Maco, Davao de Oro",
    "source": "Manila Bulletin Business",
    "date": "2026-07-09T08:35:00.000Z",
    "reason_dropped": "low_relevance"
  },
  {
    "title": "SM Prime gives trade partners a sneak peek into ₱7-billion Cebu arena",
    "source": "Manila Bulletin Business",
    "date": "2026-07-09T08:13:00.000Z",
    "reason_dropped": "low_relevance"
  },
  {
    "title": "Meralco’s ₱9-billion refund may be offset by added charges",
    "source": "Manila Bulletin Business",
    "date": "2026-07-09T08:11:00.000Z",
    "reason_dropped": "low_relevance"
  },
  {
    "title": "DigiPlus extends share buyback program to shore up growth confidence",
    "source": "Manila Bulletin Business",
    "date": "2026-07-09T07:55:00.000Z",
    "reason_dropped": "low_relevance"
  },
  {
    "title": "$60-million US MCC grant takes aim at Philippine energy bottlenecks",
    "source": "Manila Bulletin Business",
    "date": "2026-07-09T07:10:00.000Z",
    "reason_dropped": "low_relevance"
  },
  {
    "title": "Electricity bills seen rising as spot prices surge in June",
    "source": "Manila Bulletin Business",
    "date": "2026-07-09T06:04:00.000Z",
    "reason_dropped": "low_relevance"
  },
  {
    "title": "DoubleDragon-owned MerryMart moves closer to PSE exit",
    "source": "Manila Bulletin Business",
    "date": "2026-07-09T05:55:00.000Z",
    "reason_dropped": "low_relevance"
  },
  {
    "title": "PhilWeb secures exclusive deal with iGaming giant Pragmatic Play",
    "source": "Manila Bulletin Business",
    "date": "2026-07-09T05:42:00.000Z",
    "reason_dropped": "low_relevance"
  },
  {
    "title": "Aviation veteran Khalid Al Zarooni takes helm at Emirates Philippines",
    "source": "Manila Bulletin Business",
    "date": "2026-07-09T03:39:00.000Z",
    "reason_dropped": "low_relevance"
  },
  {
    "title": "ADB sees slowest post-pandemic Philippine growth in 2026",
    "source": "Manila Bulletin Business",
    "date": "2026-07-09T01:01:00.000Z",
    "reason_dropped": "low_relevance"
  },
  {
    "title": "BDO returns to debt market with sixth ASEAN sustainability bonds",
    "source": "Manila Bulletin Business",
    "date": "2026-07-09T00:35:00.000Z",
    "reason_dropped": "low_relevance"
  },
  {
    "title": "The myth about an ‘upper-middle-income’ Philippines",
    "source": "Manila Bulletin Business",
    "date": "2026-07-08T16:01:00.000Z",
    "reason_dropped": "low_relevance"
  },
  {
    "title": "Philippines ranks third globally in intangible investment growth",
    "source": "Manila Bulletin Business",
    "date": "2026-07-08T15:43:00.000Z",
    "reason_dropped": "low_relevance"
  },
  {
    "title": "Philippine economy takes bigger-than-expected hit from US-Iran war—IMF",
    "source": "Manila Bulletin Business",
    "date": "2026-07-08T13:00:00.000Z",
    "reason_dropped": "low_relevance"
  },
  {
    "title": "DOE halts landmark offshore wind power auction on geopolitical, infra risks",
    "source": "Manila Bulletin Business",
    "date": "2026-07-08T12:29:00.000Z",
    "reason_dropped": "low_relevance"
  },
  {
    "title": "Gov’t overhauls veterinary medicine approvals to protect livestock",
    "source": "Manila Bulletin Business",
    "date": "2026-07-08T10:41:00.000Z",
    "reason_dropped": "low_relevance"
  },
  {
    "title": "El Niño, geopolitical fears force gov’t to downgrade near-term economic outlook",
    "source": "Manila Bulletin Business",
    "date": "2026-07-08T10:00:00.000Z",
    "reason_dropped": "low_relevance"
  },
  {
    "title": "PSEi extends winning streak as ICTSI offsets geopolitical jitters",
    "source": "Manila Bulletin Business",
    "date": "2026-07-08T09:47:00.000Z",
    "reason_dropped": "low_relevance"
  },
  {
    "title": "PAL draws strong global investor demand with $300-million debt sale",
    "source": "Manila Bulletin Business",
    "date": "2026-07-08T09:18:00.000Z",
    "reason_dropped": "low_relevance"
  },
  {
    "title": "Business name registrations rise 5% in first half despite inflation pressure",
    "source": "Manila Bulletin Business",
    "date": "2026-07-08T08:47:00.000Z",
    "reason_dropped": "low_relevance"
  },
  {
    "title": "Megawide targets 52% profit growth in 2027 as debt cuts deliver savings",
    "source": "Manila Bulletin Business",
    "date": "2026-07-08T08:12:00.000Z",
    "reason_dropped": "low_relevance"
  },
  {
    "title": "Superpower US still too young to take path toward decline",
    "source": "Nikkei Asia Business",
    "date": "2026-07-11T10:49:16.580Z",
    "reason_dropped": "low_relevance"
  },
  {
    "title": "Mizuno enters esports market with athlete-led approach",
    "source": "Nikkei Asia Business",
    "date": "2026-07-11T10:49:16.580Z",
    "reason_dropped": "low_relevance"
  },
  {
    "title": "Japan's scallop production feels heat of climate change",
    "source": "Nikkei Asia Business",
    "date": "2026-07-11T10:49:16.580Z",
    "reason_dropped": "low_relevance"
  },
  {
    "title": "Playwright Hideki Noda tests London with play on science and humanity",
    "source": "Nikkei Asia Business",
    "date": "2026-07-11T10:49:16.580Z",
    "reason_dropped": "low_relevance"
  },
  {
    "title": "Lords of the flies: Thailand's edible insect innovators",
    "source": "Nikkei Asia Business",
    "date": "2026-07-11T10:49:16.580Z",
    "reason_dropped": "low_relevance"
  },
  {
    "title": "Subaru embraces sports car roots with revival of manual 6-speed",
    "source": "Nikkei Asia Business",
    "date": "2026-07-11T10:49:16.580Z",
    "reason_dropped": "low_relevance"
  },
  {
    "title": "Marubeni gears up for machine tool growth in India as chips, data centers boom",
    "source": "Nikkei Asia Business",
    "date": "2026-07-11T10:49:16.580Z",
    "reason_dropped": "low_relevance"
  },
  {
    "title": "SK Hynix rallies in biggest-ever foreign share sale in US",
    "source": "Nikkei Asia Business",
    "date": "2026-07-11T10:49:16.580Z",
    "reason_dropped": "low_relevance"
  },
  {
    "title": "Japan shoe store giant ABC-Mart targets big strides across Southeast Asia",
    "source": "Nikkei Asia Business",
    "date": "2026-07-11T10:49:16.580Z",
    "reason_dropped": "low_relevance"
  },
  {
    "title": "Mitsubishi Estate embarks on $9bn data center building spree in Japan",
    "source": "Nikkei Asia Business",
    "date": "2026-07-11T10:49:16.580Z",
    "reason_dropped": "low_relevance"
  },
  {
    "title": "South Korea's beauty tourism boom draws doctors away from hospital work",
    "source": "Nikkei Asia Business",
    "date": "2026-07-11T10:49:16.580Z",
    "reason_dropped": "low_relevance"
  },
  {
    "title": "Japan's Yoshinoya to bulk up ramen business with US acquisition",
    "source": "Nikkei Asia Business",
    "date": "2026-07-11T10:49:16.580Z",
    "reason_dropped": "low_relevance"
  },
  {
    "title": "China anime festival shows Japan fandom undimmed by diplomatic chill",
    "source": "Nikkei Asia Business",
    "date": "2026-07-11T10:49:16.580Z",
    "reason_dropped": "low_relevance"
  },
  {
    "title": "China's Nexchip has global ambitions as legacy chips thrive in AI's shadow",
    "source": "Nikkei Asia Business",
    "date": "2026-07-11T10:49:16.580Z",
    "reason_dropped": "low_relevance"
  },
  {
    "title": "Japan to expand research grants, seeking 20,000 Ph.Ds a year",
    "source": "Nikkei Asia Business",
    "date": "2026-07-11T10:49:16.580Z",
    "reason_dropped": "low_relevance"
  },
  {
    "title": "Miniso banks on finding the next Labubu as it opens 100 US stores",
    "source": "Nikkei Asia Business",
    "date": "2026-07-11T10:49:16.580Z",
    "reason_dropped": "low_relevance"
  },
  {
    "title": "China's BYD taps Japan luxury car dealer to drive expansion",
    "source": "Nikkei Asia Business",
    "date": "2026-07-11T10:49:16.580Z",
    "reason_dropped": "low_relevance"
  },
  {
    "title": "China steps up maritime push against Philippines, Japan, with eye on Taiwan",
    "source": "Nikkei Asia Business",
    "date": "2026-07-11T10:49:16.580Z",
    "reason_dropped": "low_relevance"
  },
  {
    "title": "Yen rises, JGB yields fall on Japan finance minister's pension fund remarks",
    "source": "Nikkei Asia Business",
    "date": "2026-07-11T10:49:16.580Z",
    "reason_dropped": "low_relevance"
  },
  {
    "title": "Japan's JAPEX aims to nearly quadruple US oil, gas output by 2035",
    "source": "Nikkei Asia Business",
    "date": "2026-07-11T10:49:16.580Z",
    "reason_dropped": "low_relevance"
  },
  {
    "title": "SoftBank and PayPay offer to invest up to $1.9bn in 7-Eleven parent",
    "source": "Nikkei Asia Business",
    "date": "2026-07-11T10:49:16.580Z",
    "reason_dropped": "low_relevance"
  },
  {
    "title": "Malaysia's Johor vote tests Anwar's support ahead of general election",
    "source": "Nikkei Asia Business",
    "date": "2026-07-11T10:49:16.580Z",
    "reason_dropped": "low_relevance"
  },
  {
    "title": "China successfully recovers rocket at sea in push for reusable launches",
    "source": "Nikkei Asia Business",
    "date": "2026-07-11T10:49:16.580Z",
    "reason_dropped": "low_relevance"
  },
  {
    "title": "Taiwan's top memory chip maker Nanya Tech to quadruple 2027 capex",
    "source": "Nikkei Asia Business",
    "date": "2026-07-11T10:49:16.580Z",
    "reason_dropped": "low_relevance"
  },
  {
    "title": "Japan weighs dedicated agency to support Self-Defense Forces retirees",
    "source": "Nikkei Asia Business",
    "date": "2026-07-11T10:49:16.580Z",
    "reason_dropped": "low_relevance"
  },
  {
    "title": "Australian workers vow strike at world's largest iron ore bulk export port",
    "source": "Nikkei Asia Business",
    "date": "2026-07-11T10:49:16.580Z",
    "reason_dropped": "low_relevance"
  },
  {
    "title": "Japan and India must harness middle-power momentum in the Indo-Pacific",
    "source": "Nikkei Asia Business",
    "date": "2026-07-11T10:49:16.580Z",
    "reason_dropped": "low_relevance"
  },
  {
    "title": "Hong Kong looks beyond Iran war in cultivating China-Mideast business",
    "source": "Nikkei Asia Business",
    "date": "2026-07-11T10:49:16.580Z",
    "reason_dropped": "low_relevance"
  },
  {
    "title": "Editor's Choice: War and high fuel costs reshape Asia's vacation plans",
    "source": "Nikkei Asia Business",
    "date": "2026-07-11T10:49:16.580Z",
    "reason_dropped": "low_relevance"
  },
  {
    "title": "Japan prefecture offers reward to root out illegal foreign worker hiring",
    "source": "Nikkei Asia Business",
    "date": "2026-07-11T10:49:16.580Z",
    "reason_dropped": "low_relevance"
  },
  {
    "title": "Pakistan mediates between Libya's two administrations after US-Iran talks",
    "source": "Nikkei Asia Business",
    "date": "2026-07-11T10:49:16.580Z",
    "reason_dropped": "low_relevance"
  },
  {
    "title": "Japan's Kirin bets on Asian expansion to grow health science business",
    "source": "Nikkei Asia Business",
    "date": "2026-07-11T10:49:16.580Z",
    "reason_dropped": "low_relevance"
  },
  {
    "title": "Grab to expand Vietnam EV charging network fifteenfold by 2028",
    "source": "Nikkei Asia Business",
    "date": "2026-07-11T10:49:16.580Z",
    "reason_dropped": "low_relevance"
  },
  {
    "title": "Beijing and Tokyo can learn from China's 'Hong Kong of the north'",
    "source": "Nikkei Asia Business",
    "date": "2026-07-11T10:49:16.580Z",
    "reason_dropped": "low_relevance"
  },
  {
    "title": "Tibetan activists chain themselves to UN gates after fatal self-immolation",
    "source": "Nikkei Asia Business",
    "date": "2026-07-11T10:49:16.580Z",
    "reason_dropped": "low_relevance"
  },
  {
    "title": "SK Hynix: South Korean memory chip titan raises $26.5bn in the US",
    "source": "Nikkei Asia Business",
    "date": "2026-07-11T10:49:16.580Z",
    "reason_dropped": "low_relevance"
  },
  {
    "title": "Beijing's acts dilute impact of South China Sea award, Manila's lawyer says",
    "source": "Nikkei Asia Business",
    "date": "2026-07-11T10:49:16.580Z",
    "reason_dropped": "low_relevance"
  },
  {
    "title": "Japan's Taisei, Fanuc develop AI warehouse that doubles space efficiency",
    "source": "Nikkei Asia Business",
    "date": "2026-07-11T10:49:16.580Z",
    "reason_dropped": "low_relevance"
  },
  {
    "title": "Tesla's profit per vehicle drops 40%, within Toyota's striking range",
    "source": "Nikkei Asia Business",
    "date": "2026-07-11T10:49:16.580Z",
    "reason_dropped": "low_relevance"
  },
  {
    "title": "Japan to test launch reusable rocket in chase with SpaceX",
    "source": "Nikkei Asia Business",
    "date": "2026-07-11T10:49:16.580Z",
    "reason_dropped": "low_relevance"
  },
  {
    "title": "Is Pakistan turning its side of Kashmir into another Balochistan?",
    "source": "Nikkei Asia Business",
    "date": "2026-07-11T10:49:16.580Z",
    "reason_dropped": "low_relevance"
  },
  {
    "title": "Tokyo office vacancies fall below 2% for 1st time since pandemic",
    "source": "Nikkei Asia Business",
    "date": "2026-07-11T10:49:16.580Z",
    "reason_dropped": "low_relevance"
  },
  {
    "title": "Asian allies build up missile production as US stockpile dwindles",
    "source": "Nikkei Asia Business",
    "date": "2026-07-11T10:49:16.580Z",
    "reason_dropped": "low_relevance"
  },
  {
    "title": "Nestle to build $690m plant in Thailand for Nescafe coffee",
    "source": "Nikkei Asia Business",
    "date": "2026-07-11T10:49:16.580Z",
    "reason_dropped": "low_relevance"
  },
  {
    "title": "Onitsuka Tiger's flagship store in Tokyo boasts 'Street Fighter' arcade",
    "source": "Nikkei Asia Business",
    "date": "2026-07-11T10:49:16.580Z",
    "reason_dropped": "low_relevance"
  },
  {
    "title": "Teardown of cheap USB drives shows storage capacity faked via microSD card",
    "source": "Nikkei Asia Business",
    "date": "2026-07-11T10:49:16.580Z",
    "reason_dropped": "low_relevance"
  },
  {
    "title": "Japan moves quicker to lower travel risk advisories, easing business trips",
    "source": "Nikkei Asia Business",
    "date": "2026-07-11T10:49:16.580Z",
    "reason_dropped": "low_relevance"
  },
  {
    "title": "ANA's domestic fare revamp brings it closer to a budget airline",
    "source": "Nikkei Asia Business",
    "date": "2026-07-11T10:49:16.580Z",
    "reason_dropped": "low_relevance"
  },
  {
    "title": "7-Eleven parent's net profit jumps 24%, fueled by US gasoline prices",
    "source": "Nikkei Asia Business",
    "date": "2026-07-11T10:49:16.580Z",
    "reason_dropped": "low_relevance"
  },
  {
    "title": "Walmart targets Japanese food as US inflation brings wealthier shoppers",
    "source": "Nikkei Asia Business",
    "date": "2026-07-11T10:49:16.580Z",
    "reason_dropped": "low_relevance"
  },
  {
    "title": "Yen climbs as Japan lures pension funds into domestic assets",
    "source": "The Business Times Banking",
    "date": "2026-07-10T12:44:37.000Z",
    "reason_dropped": "low_relevance"
  },
  {
    "title": "BOJ may raise growth forecast, maintain vigilance to inflation risk",
    "source": "The Business Times Banking",
    "date": "2026-07-10T08:51:03.000Z",
    "reason_dropped": "low_relevance"
  },
  {
    "title": "Yen rises as Japan encourages pension funds to invest in domestic assets",
    "source": "The Business Times Banking",
    "date": "2026-07-10T03:53:16.000Z",
    "reason_dropped": "low_relevance"
  },
  {
    "title": "US dollar drifts with oil; Gulf tensions, Fed minutes in focus",
    "source": "The Business Times Banking",
    "date": "2026-07-09T12:34:41.000Z",
    "reason_dropped": "low_relevance"
  },
  {
    "title": "Asia growth improves but ADB warns of persistent headwinds",
    "source": "The Business Times Banking",
    "date": "2026-07-09T08:37:46.000Z",
    "reason_dropped": "low_relevance"
  },
  {
    "title": "Bank of Japan sees growing inflation pressures from Middle East war",
    "source": "The Business Times Banking",
    "date": "2026-07-09T07:46:21.000Z",
    "reason_dropped": "low_relevance"
  },
  {
    "title": "DBS, OCBC, UOB push STI to new highs as institutions pile in ahead of earnings",
    "source": "The Business Times Banking",
    "date": "2026-07-09T01:55:47.000Z",
    "reason_dropped": "low_relevance"
  },
  {
    "title": "Malaysia may hold policy rate, signal upcoming hike as AI boosts economic growth",
    "source": "The Business Times Banking",
    "date": "2026-07-09T00:38:24.000Z",
    "reason_dropped": "low_relevance"
  },
  {
    "title": "Fed policymakers’ inflation concerns grew at June meeting, minutes show",
    "source": "The Business Times Banking",
    "date": "2026-07-08T22:43:47.000Z",
    "reason_dropped": "low_relevance"
  },
  {
    "title": "PBOC pledges to maintain accommodative policy amid weak demand, external shocks",
    "source": "The Business Times Banking",
    "date": "2026-07-08T13:42:39.000Z",
    "reason_dropped": "low_relevance"
  },
  {
    "title": "Bitcoin weakens as Trump’s remarks raise fresh Iran war concerns",
    "source": "The Business Times Banking",
    "date": "2026-07-08T13:16:35.000Z",
    "reason_dropped": "low_relevance"
  },
  {
    "title": "US dollar steady around 1-week high after Trump says Iran MOU ‘over’",
    "source": "The Business Times Banking",
    "date": "2026-07-08T12:22:46.000Z",
    "reason_dropped": "low_relevance"
  },
  {
    "title": "Japan considers policy wording change as BOJ independence fears roil bonds",
    "source": "The Business Times Banking",
    "date": "2026-07-08T05:07:59.000Z",
    "reason_dropped": "low_relevance"
  },
  {
    "title": "New Zealand raises rates by 25 bps to 2.5%, flags further hikes to curb inflation pressures",
    "source": "The Business Times Banking",
    "date": "2026-07-08T03:06:54.000Z",
    "reason_dropped": "low_relevance"
  },
  {
    "title": "South Korea to closely watch risks around stock market volatility",
    "source": "The Business Times Banking",
    "date": "2026-07-08T01:51:01.000Z",
    "reason_dropped": "low_relevance"
  },
  {
    "title": "Australia central banker says oil shock yet to slow economy",
    "source": "The Business Times Banking",
    "date": "2026-07-08T01:27:12.000Z",
    "reason_dropped": "low_relevance"
  },
  {
    "title": "What is a protected cell company and how could it benefit businesses?",
    "source": "The Business Times Banking",
    "date": "2026-07-08T00:00:00.000Z",
    "reason_dropped": "low_relevance"
  },
  {
    "title": "Yen pinned near 40-year low with investors wary of intervention",
    "source": "The Business Times Banking",
    "date": "2026-07-07T12:39:08.000Z",
    "reason_dropped": "low_relevance"
  },
  {
    "title": "HSBC reins in riskier private credit lending: FT",
    "source": "The Business Times Banking",
    "date": "2026-07-07T05:17:17.000Z",
    "reason_dropped": "low_relevance"
  },
  {
    "title": "Beijing bolsters Hong Kong bond, gold trading in global renminbi push",
    "source": "The Business Times Banking",
    "date": "2026-07-07T04:47:10.000Z",
    "reason_dropped": "low_relevance"
  },
  {
    "title": "DBS, OCBC and UOB shares hit all-time highs as sentiment improves",
    "source": "The Business Times Banking",
    "date": "2026-07-07T02:01:20.000Z",
    "reason_dropped": "low_relevance"
  },
  {
    "title": "Japan drives Asia offshore bonds to record, surpassing China era",
    "source": "The Business Times Banking",
    "date": "2026-07-07T00:06:56.000Z",
    "reason_dropped": "low_relevance"
  },
  {
    "title": "Europe’s central banks may come under political pressure, Panetta says",
    "source": "The Business Times Banking",
    "date": "2026-07-06T23:49:55.000Z",
    "reason_dropped": "low_relevance"
  },
  {
    "title": "Wall Street regulator should stick to quarterly reports, investor groups say",
    "source": "The Business Times Banking",
    "date": "2026-07-06T23:02:17.000Z",
    "reason_dropped": "low_relevance"
  },
  {
    "title": "Blackstone, CVC and MUFG among bidders for stake in Vietnam’s fintech firm MoMo: sources",
    "source": "The Business Times Banking",
    "date": "2026-07-06T12:55:38.000Z",
    "reason_dropped": "low_relevance"
  },
  {
    "title": "Philippine economy can handle one more rate hike, central bank governor says",
    "source": "The Business Times Banking",
    "date": "2026-07-06T08:34:30.000Z",
    "reason_dropped": "low_relevance"
  },
  {
    "title": "Moody’s warns Asia-Pacific private credit expansion to slow",
    "source": "The Business Times Banking",
    "date": "2026-07-06T07:08:03.000Z",
    "reason_dropped": "low_relevance"
  },
  {
    "title": "Goldman cuts yen forecast to 165 per US dollar, likes carry trades",
    "source": "The Business Times Banking",
    "date": "2026-07-06T03:42:19.000Z",
    "reason_dropped": "low_relevance"
  },
  {
    "title": "China steps up financial risk cleanup under new top regulator",
    "source": "The Business Times Banking",
    "date": "2026-07-06T03:14:44.000Z",
    "reason_dropped": "low_relevance"
  },
  {
    "title": "PayNow eyes merchant, business payments in next growth phase, puts heat on card networks",
    "source": "The Business Times Banking",
    "date": "2026-07-06T02:47:17.000Z",
    "reason_dropped": "low_relevance"
  },
  {
    "title": "Record wave of IPO lock-up shares to hit Hong Kong market",
    "source": "The Business Times Banking",
    "date": "2026-07-06T01:15:24.000Z",
    "reason_dropped": "low_relevance"
  },
  {
    "title": "Bankers say Asia loan market to stay weak as war saps confidence",
    "source": "The Business Times Banking",
    "date": "2026-07-06T01:06:56.000Z",
    "reason_dropped": "low_relevance"
  },
  {
    "title": "Revised takeover code: Dealmakers welcome targeted guidance instead of ban on deal protection",
    "source": "The Business Times Banking",
    "date": "2026-07-05T23:00:00.000Z",
    "reason_dropped": "low_relevance"
  },
  {
    "title": "Vietnam domestic airfares hit six-year low with tickets from $25",
    "source": "VNExpress Business",
    "date": "2026-07-09T07:35:42.000Z",
    "reason_dropped": "hard_excluded_event_promo"
  },
  {
    "title": "Masan Group chairman Nguyen Dang Quang briefly loses billionaire status",
    "source": "VNExpress Business",
    "date": "2026-07-11T03:44:33.000Z",
    "reason_dropped": "low_relevance"
  },
  {
    "title": "Singapore lender UOB raises Vietnam economic growth forecast to 8.5%",
    "source": "VNExpress Business",
    "date": "2026-07-11T00:14:50.000Z",
    "reason_dropped": "low_relevance"
  },
  {
    "title": "Another Bac Ninh housing project approved to sell to foreigners",
    "source": "VNExpress Business",
    "date": "2026-07-11T04:30:00.000Z",
    "reason_dropped": "low_relevance"
  },
  {
    "title": "Techcombank co-organizes Vietnam Financial Forum 2026",
    "source": "VNExpress Business",
    "date": "2026-07-11T02:00:00.000Z",
    "reason_dropped": "low_relevance"
  },
  {
    "title": "Dollar strengthens against dong",
    "source": "VNExpress Business",
    "date": "2026-07-10T04:32:57.000Z",
    "reason_dropped": "low_relevance"
  },
  {
    "title": "Gold prices rise",
    "source": "VNExpress Business",
    "date": "2026-07-10T04:12:41.000Z",
    "reason_dropped": "low_relevance"
  },
  {
    "title": "Car ownership certificate in world's most expensive city hits record nearly $100K",
    "source": "VNExpress Business",
    "date": "2026-07-10T04:10:38.000Z",
    "reason_dropped": "low_relevance"
  },
  {
    "title": "Vietnam buys $121M worth of diamonds in H1",
    "source": "VNExpress Business",
    "date": "2026-07-10T04:10:18.000Z",
    "reason_dropped": "low_relevance"
  },
  {
    "title": "Vietnam to remain Southeast Asia's fastest-growing economy: ADB",
    "source": "VNExpress Business",
    "date": "2026-07-10T04:09:58.000Z",
    "reason_dropped": "low_relevance"
  },
  {
    "title": "Sun Group, Accor elevate partnership with nearly 6,000 hotel rooms and serviced apartments",
    "source": "VNExpress Business",
    "date": "2026-07-10T02:00:00.000Z",
    "reason_dropped": "low_relevance"
  },
  {
    "title": "Gasoline prices drop",
    "source": "VNExpress Business",
    "date": "2026-07-09T09:25:10.000Z",
    "reason_dropped": "low_relevance"
  },
  {
    "title": "1.5 million Singaporeans to receive up to $660 cash payouts in August",
    "source": "VNExpress Business",
    "date": "2026-07-09T08:13:05.000Z",
    "reason_dropped": "low_relevance"
  },
  {
    "title": "Gold prices tiptoe up",
    "source": "VNExpress Business",
    "date": "2026-07-09T08:12:44.000Z",
    "reason_dropped": "low_relevance"
  },
  {
    "title": "Thailand’s 5th richest man Charoen Sirivadhanabhakdi's Frasers Property launches Singapore condo with units from $1.1M",
    "source": "VNExpress Business",
    "date": "2026-07-09T07:43:29.000Z",
    "reason_dropped": "low_relevance"
  },
  {
    "title": "Philippine Airlines, controlled by Philippines’ 3rd richest man Lucio Tan, raises $300M through bonds",
    "source": "VNExpress Business",
    "date": "2026-07-09T07:43:07.000Z",
    "reason_dropped": "low_relevance"
  },
  {
    "title": "Musang King durian prices hit record low at $1.9 per kg",
    "source": "VNExpress Business",
    "date": "2026-07-09T07:36:07.000Z",
    "reason_dropped": "low_relevance"
  },
  {
    "title": "Dollar inches up against dong",
    "source": "VNExpress Business",
    "date": "2026-07-09T07:35:18.000Z",
    "reason_dropped": "low_relevance"
  },
  {
    "title": "Hong Kong falls to 4th among world’s costliest cities for wealthy individuals",
    "source": "VNExpress Business",
    "date": "2026-07-08T23:38:08.000Z",
    "reason_dropped": "low_relevance"
  },
  {
    "title": "Durians to be auctioned at farms for first time in Central Highlands province",
    "source": "VNExpress Business",
    "date": "2026-07-08T23:37:52.000Z",
    "reason_dropped": "low_relevance"
  },
  {
    "title": "Thai Singha beer empire heir's mother drops 'ungrateful child' suit",
    "source": "VNExpress Business",
    "date": "2026-07-08T23:37:11.000Z",
    "reason_dropped": "low_relevance"
  },
  {
    "title": "From duty-free fortune to wagyu beef empire: Hong Kong-born Singaporean Bruce Cheung starts over at 60",
    "source": "VNExpress Business",
    "date": "2026-07-08T23:08:28.000Z",
    "reason_dropped": "low_relevance"
  },
  {
    "title": "Which city leads Asia in number of billionaires?",
    "source": "VNExpress Business",
    "date": "2026-07-08T23:08:13.000Z",
    "reason_dropped": "low_relevance"
  },
  {
    "title": "The story behind UOB Plaza HCMC's shell-inspired design",
    "source": "VNExpress Business",
    "date": "2026-07-09T12:00:00.000Z",
    "reason_dropped": "low_relevance"
  },
  {
    "title": "Technology, finance firms pledge support for Hanoi's development",
    "source": "VNExpress Business",
    "date": "2026-07-09T03:00:00.000Z",
    "reason_dropped": "low_relevance"
  },
  {
    "title": "Singapore’s 3 biggest banks’ stocks scale record highs in same session",
    "source": "VNExpress Business",
    "date": "2026-07-08T09:14:32.000Z",
    "reason_dropped": "low_relevance"
  },
  {
    "title": "Gold prices continue to slide",
    "source": "VNExpress Business",
    "date": "2026-07-08T09:10:03.000Z",
    "reason_dropped": "low_relevance"
  },
  {
    "title": "Gold prices slip",
    "source": "VNExpress Business",
    "date": "2026-07-08T07:33:27.000Z",
    "reason_dropped": "low_relevance"
  },
  {
    "title": "Dollar gains over dong",
    "source": "VNExpress Business",
    "date": "2026-07-08T07:32:41.000Z",
    "reason_dropped": "low_relevance"
  },
  {
    "title": "Malaysia’s most expensive durian Tupai King retains crown as Musang King prices tumble",
    "source": "VNExpress Business",
    "date": "2026-07-08T04:44:41.000Z",
    "reason_dropped": "low_relevance"
  },
  {
    "title": "Thailand investigates unknown investor’s $1B stake in second largest telecom firm True",
    "source": "VNExpress Business",
    "date": "2026-07-08T04:44:22.000Z",
    "reason_dropped": "low_relevance"
  },
  {
    "title": "One of the world’s top durian exporters faces glut after years of China-fueled expansion",
    "source": "VNExpress Business",
    "date": "2026-07-08T03:43:35.000Z",
    "reason_dropped": "low_relevance"
  },
  {
    "title": "Singapore-owned Frasers Property Australia sells Sydney mall for $172M",
    "source": "VNExpress Business",
    "date": "2026-07-08T03:20:29.000Z",
    "reason_dropped": "low_relevance"
  },
  {
    "title": "Hotel101, backed by Jollibee billionaire, plans $200M Thailand expansion",
    "source": "VNExpress Business",
    "date": "2026-07-08T03:20:10.000Z",
    "reason_dropped": "low_relevance"
  },
  {
    "title": "Singapore holds ground as world’s most expensive city for the rich, ahead of Zurich, Monaco",
    "source": "VNExpress Business",
    "date": "2026-07-08T02:33:14.000Z",
    "reason_dropped": "low_relevance"
  },
  {
    "title": "Which is the most livable city in Southeast Asia in 2026?",
    "source": "VNExpress Business",
    "date": "2026-07-07T23:24:50.000Z",
    "reason_dropped": "low_relevance"
  },
  {
    "title": "I’m still empty-handed 30 years after parents promised me inheritance",
    "source": "VNExpress Business",
    "date": "2026-07-07T23:11:11.000Z",
    "reason_dropped": "low_relevance"
  },
  {
    "title": "Japanese brewer Sapporo to invest $643M in Singapore-based venture with Carlsberg",
    "source": "VNExpress Business",
    "date": "2026-07-07T09:46:43.000Z",
    "reason_dropped": "low_relevance"
  },
  {
    "title": "Coffee exports reach $4.78B in H1",
    "source": "VNExpress Business",
    "date": "2026-07-07T09:46:26.000Z",
    "reason_dropped": "low_relevance"
  },
  {
    "title": "Gold prices decline for 2nd time Tuesday",
    "source": "VNExpress Business",
    "date": "2026-07-07T09:46:05.000Z",
    "reason_dropped": "low_relevance"
  },
  {
    "title": "Dollar edges down against dong on black market",
    "source": "VNExpress Business",
    "date": "2026-07-07T08:09:59.000Z",
    "reason_dropped": "low_relevance"
  },
  {
    "title": "Gold prices fall",
    "source": "VNExpress Business",
    "date": "2026-07-07T07:33:55.000Z",
    "reason_dropped": "low_relevance"
  },
  {
    "title": "Malaysia targets 50% cut in food imports by 2050",
    "source": "VNExpress Business",
    "date": "2026-07-07T07:33:40.000Z",
    "reason_dropped": "low_relevance"
  },
  {
    "title": "Textile, garment exports rise in H1",
    "source": "VNExpress Business",
    "date": "2026-07-07T07:33:25.000Z",
    "reason_dropped": "low_relevance"
  },
  {
    "title": "Citi sees Vietnam as key market for social finance growth",
    "source": "VNExpress Business",
    "date": "2026-07-07T08:00:00.000Z",
    "reason_dropped": "low_relevance"
  },
  {
    "title": "7-Eleven sues Nike over Air Max with chain's tri-color stripe design",
    "source": "VNExpress Business",
    "date": "2026-07-06T09:21:26.000Z",
    "reason_dropped": "low_relevance"
  },
  {
    "title": "Hong Kong schools fuel property recovery with purchases, leases",
    "source": "VNExpress Business",
    "date": "2026-07-06T08:48:58.000Z",
    "reason_dropped": "low_relevance"
  },
  {
    "title": "Gold prices drop",
    "source": "VNExpress Business",
    "date": "2026-07-06T08:48:41.000Z",
    "reason_dropped": "low_relevance"
  },
  {
    "title": "Dollar slides against dong",
    "source": "VNExpress Business",
    "date": "2026-07-06T08:48:24.000Z",
    "reason_dropped": "low_relevance"
  },
  {
    "title": "Calls for Malaysia to mandate free drinking water at eateries spark debate",
    "source": "VNExpress Business",
    "date": "2026-07-06T08:48:07.000Z",
    "reason_dropped": "low_relevance"
  },
  {
    "title": "Durian prices fall to $1 per kg as rainy weather affects quality",
    "source": "VNExpress Business",
    "date": "2026-07-06T03:40:04.000Z",
    "reason_dropped": "low_relevance"
  },
  {
    "title": "Three Singapore shophouses sold to firm linked to Tat Lee Bank’s founding family for $54M",
    "source": "VNExpress Business",
    "date": "2026-07-06T03:30:37.000Z",
    "reason_dropped": "low_relevance"
  },
  {
    "title": "Singapore porridge shop owner accused of buying Lamborghini with proceeds from $2.9M tax evasion",
    "source": "VNExpress Business",
    "date": "2026-07-05T23:04:07.000Z",
    "reason_dropped": "low_relevance"
  },
  {
    "title": "Chinese tea chain Molly Tea ordered to pay Louis Vuitton $1.5M over logo dispute",
    "source": "VNExpress Business",
    "date": "2026-07-05T23:03:27.000Z",
    "reason_dropped": "low_relevance"
  },
  {
    "title": "Who are Singapore’s 3 highest-paid bank CEOs?",
    "source": "VNExpress Business",
    "date": "2026-07-05T22:46:51.000Z",
    "reason_dropped": "low_relevance"
  },
  {
    "title": "FPT outlines AI adoption roadmap for Japanese business leaders",
    "source": "VNExpress Business",
    "date": "2026-07-06T10:30:00.000Z",
    "reason_dropped": "low_relevance"
  },
  {
    "title": "Uncertainty is a given but Vietnam remains a long-term growth story: UOB CEO",
    "source": "VNExpress Business",
    "date": "2026-07-06T01:00:00.000Z",
    "reason_dropped": "low_relevance"
  },
  {
    "title": "China snaps up Vietnamese lobsters worth $506M in 5 months",
    "source": "VNExpress Business",
    "date": "2026-07-05T04:05:15.000Z",
    "reason_dropped": "low_relevance"
  },
  {
    "title": "Hong Kong graduates struggle to find entry-level roles as AI reshapes job market",
    "source": "VNExpress Business",
    "date": "2026-07-04T10:32:07.000Z",
    "reason_dropped": "low_relevance"
  },
  {
    "title": "Dollar weakens against dong on black market",
    "source": "VNExpress Business",
    "date": "2026-07-04T10:31:23.000Z",
    "reason_dropped": "low_relevance"
  },
  {
    "title": "Bangko Sentral ng Pilipinas Discount Window Facility interest rates effective 08 July 2026",
    "source": "Bangko Sentral ng Pilipinas",
    "date": "2026-07-07T09:40:24.000Z",
    "reason_dropped": "hard_excluded_commerce"
  },
  {
    "title": "BSP promotes employer-sponsored PERA to strengthen workers' retirement security",
    "source": "Bangko Sentral ng Pilipinas",
    "date": "2026-07-10T03:20:53.000Z",
    "reason_dropped": "low_relevance"
  },
  {
    "title": "FDI reaches US$2.0B in January-April 2026",
    "source": "Bangko Sentral ng Pilipinas",
    "date": "2026-07-10T07:07:35.000Z",
    "reason_dropped": "low_relevance"
  },
  {
    "title": "BSP launches book on financial system crises, resilience",
    "source": "Bangko Sentral ng Pilipinas",
    "date": "2026-07-09T04:35:23.000Z",
    "reason_dropped": "low_relevance"
  },
  {
    "title": "Inflation drops further to 6.4 percent in June",
    "source": "Bangko Sentral ng Pilipinas",
    "date": "2026-07-07T07:47:56.000Z",
    "reason_dropped": "low_relevance"
  },
  {
    "title": "Bank lending expands by 12.1% in May",
    "source": "Bangko Sentral ng Pilipinas",
    "date": "2026-07-07T11:05:32.000Z",
    "reason_dropped": "low_relevance"
  },
  {
    "title": "Domestic liquidity grows by 12.8% in May",
    "source": "Bangko Sentral ng Pilipinas",
    "date": "2026-07-07T11:07:54.000Z",
    "reason_dropped": "low_relevance"
  },
  {
    "title": "Country's foreign reserves rise to US$104.8 billion as of end-June 2026",
    "source": "Bangko Sentral ng Pilipinas",
    "date": "2026-07-07T13:22:06.000Z",
    "reason_dropped": "low_relevance"
  },
  {
    "title": "Inflation, bumaba pa sa 6.4% nitong Hunyo",
    "source": "Bangko Sentral ng Pilipinas",
    "date": "2026-07-10T03:51:34.000Z",
    "reason_dropped": "low_relevance"
  },
  {
    "title": "Malacañang reappoints MBMs Wassmer, Querubin",
    "source": "Bangko Sentral ng Pilipinas",
    "date": "2026-07-03T03:22:04.000Z",
    "reason_dropped": "low_relevance"
  },
  {
    "title": "Call for nominations: Financial Health and Inclusion Excellence Awards",
    "source": "Bangko Sentral ng Pilipinas",
    "date": "2026-07-02T03:31:09.000Z",
    "reason_dropped": "low_relevance"
  },
  {
    "title": "Statement on World Bank raising PH to upper middle-income status",
    "source": "Bangko Sentral ng Pilipinas",
    "date": "2026-07-02T07:42:52.000Z",
    "reason_dropped": "low_relevance"
  },
  {
    "title": "Panawagan para sa mga nominasyon: Financial Health and Inclusion Excellence Awards",
    "source": "Bangko Sentral ng Pilipinas",
    "date": "2026-07-07T03:13:08.000Z",
    "reason_dropped": "low_relevance"
  },
  {
    "title": "BSP: Potential CBDC uses include securities settlement and int'l. payments",
    "source": "Bangko Sentral ng Pilipinas",
    "date": "2026-07-01T02:27:31.000Z",
    "reason_dropped": "low_relevance"
  },
  {
    "title": "BSP, WB promote digitalization of government transactions",
    "source": "Bangko Sentral ng Pilipinas",
    "date": "2026-06-29T10:22:00.000Z",
    "reason_dropped": "low_relevance"
  },
  {
    "title": "FCDU loans decreased by 0.8% to US$15.44 billion in Q1 2026",
    "source": "Bangko Sentral ng Pilipinas",
    "date": "2026-06-30T05:29:21.000Z",
    "reason_dropped": "low_relevance"
  },
  {
    "title": "Month-ahead inflation forecast for June 2026",
    "source": "Bangko Sentral ng Pilipinas",
    "date": "2026-06-30T08:11:59.000Z",
    "reason_dropped": "low_relevance"
  },
  {
    "title": "The Philippines’ net external liability position widened as of end-March 2026",
    "source": "Bangko Sentral ng Pilipinas",
    "date": "2026-06-30T15:07:02.000Z",
    "reason_dropped": "low_relevance"
  },
  {
    "title": "Pagtaya sa inflation sa Hunyo 2026",
    "source": "Bangko Sentral ng Pilipinas",
    "date": "2026-07-02T03:45:46.000Z",
    "reason_dropped": "low_relevance"
  },
  {
    "title": "BSP amends e-payments framework to promote more affordable digital transactions",
    "source": "Bangko Sentral ng Pilipinas",
    "date": "2026-06-28T03:49:18.000Z",
    "reason_dropped": "low_relevance"
  },
  {
    "title": "Consumer confidence declines amid expectation of weaker economic and tighter household financial conditions[1]",
    "source": "Bangko Sentral ng Pilipinas",
    "date": "2026-06-26T04:41:41.000Z",
    "reason_dropped": "low_relevance"
  },
  {
    "title": "Business confidence improves as firms expect favorable corporate earnings and lower oil prices[1]",
    "source": "Bangko Sentral ng Pilipinas",
    "date": "2026-06-26T04:53:05.000Z",
    "reason_dropped": "low_relevance"
  },
  {
    "title": "BSP strengthens rules to safeguard financial consumers in digital marketplaces and platforms",
    "source": "Bangko Sentral ng Pilipinas",
    "date": "2026-06-26T06:02:14.000Z",
    "reason_dropped": "low_relevance"
  },
  {
    "title": "BOP posts wider deficit in Q1 2026 amid external debt repayments and higher import costs",
    "source": "Bangko Sentral ng Pilipinas",
    "date": "2026-06-26T09:52:57.000Z",
    "reason_dropped": "low_relevance"
  },
  {
    "title": "BSP sees continued external sector challenges in 2026-2027",
    "source": "Bangko Sentral ng Pilipinas",
    "date": "2026-06-26T11:24:03.000Z",
    "reason_dropped": "low_relevance"
  },
  {
    "title": "Property prices accelerate in Q1 2026",
    "source": "Bangko Sentral ng Pilipinas",
    "date": "2026-06-26T11:54:27.000Z",
    "reason_dropped": "low_relevance"
  },
  {
    "title": "DOF welcomes IIF assessment as PH tops emerging markets in investor relations, supporting more investments and jobs",
    "source": "Department of Finance",
    "date": "2026-07-10T05:34:08.000Z",
    "reason_dropped": "low_relevance"
  },
  {
    "title": "PH secures US$60-Million MCC Threshold Program grant to advance energy security and governance reforms",
    "source": "Department of Finance",
    "date": "2026-07-09T03:04:03.000Z",
    "reason_dropped": "low_relevance"
  },
  {
    "title": "193rd DBCC Joint Statement",
    "source": "Department of Finance",
    "date": "2026-07-08T09:27:47.000Z",
    "reason_dropped": "low_relevance"
  },
  {
    "title": "Sec. Frederick Go lauds GOCCs for higher dividend remittances, delivering high returns for the Filipino People",
    "source": "Department of Finance",
    "date": "2026-07-08T08:32:05.000Z",
    "reason_dropped": "low_relevance"
  },
  {
    "title": "Opening Remarks2026 GOCCs Day",
    "source": "Department of Finance",
    "date": "2026-07-08T08:23:27.000Z",
    "reason_dropped": "low_relevance"
  },
  {
    "title": "PH, Korea advance strategic investments to create jobs and strengthen industries",
    "source": "Department of Finance",
    "date": "2026-07-08T04:01:32.000Z",
    "reason_dropped": "low_relevance"
  },
  {
    "title": "DOF GOCC Service Caravan Brings One-Stop Government Services to Thousands in Cagayan de Oro",
    "source": "Department of Finance",
    "date": "2026-07-07T07:29:02.000Z",
    "reason_dropped": "low_relevance"
  },
  {
    "title": "PH, Denmark Sign MOU on Financial and Developmental Cooperation",
    "source": "Department of Finance",
    "date": "2026-07-06T06:47:26.000Z",
    "reason_dropped": "low_relevance"
  },
  {
    "title": "Statement of Finance Secretary Frederick D. Go on RCBC’s free transfers",
    "source": "Department of Finance",
    "date": "2026-07-04T03:47:41.000Z",
    "reason_dropped": "low_relevance"
  },
  {
    "title": "Statement of DOF Secretary Frederick D. Go on World Bank announcement on UMIC",
    "source": "Department of Finance",
    "date": "2026-07-02T00:44:48.000Z",
    "reason_dropped": "low_relevance"
  }
]